{"name":"11X.01.23 Message Types - Chat - AllowAll - Org-User sendet ein m.video Attachment (mov) über Matrix-Protokoll v1.11 an Org-User","id":"11x.-(1)-message-types-(basis-spec);11x.01.23-message-types---chat---allowall---org-user-sendet-ein-m.video-attachment-(mov)-über-matrix-protokoll-v1.11-an-org-user","scenarioId":"UCs_Basis/UC11X_MessageTypes/11X_1_OrgOrg_MessageTypes_V2_Basis:11X.01.23 Message Types - Chat - AllowAll - Org-User sendet ein m.video Attachment (mov) über Matrix-Protokoll v1.11 an Org-User","methodName":"11X.01.23 Message Types - Chat - AllowAll - Org-User sendet ein m.video Attachment (mov) über Matrix-Protokoll v1.11 an Org-User","testSteps":[{"number":1,"description":"1: 11X.01.23 Message Types - Chat - AllowAll - Org-User sendet ein m.video Attachment (mov) über Matrix-Protokoll v1.11 an Org-User ({ApiName1\u003dRU1-Ref-Pract-SDK-HS1, ApiName2\u003dRU1-Ref-Pract-SDK-HS2})","duration":74892,"startTime":"2026-01-11T20:20:01.517110985+01:00[Europe/Berlin]","result":"SUCCESS","reportData":[{"title":"TestcaseId","contents":"@TCID:TIM_V2_BASIS_AF_11X0123/9a5ac82f-fec9-4de2-a74f-3c51b2bf82c6","isEvidence":false,"id":"report-data-14b95942-be50-4cff-89db-8988a4573a75"}],"precondition":false,"level":0,"lineNumber":443,"children":[{"number":2,"description":"Angenommen Es werden folgende Clients reserviert:\n| A | PRO_CLIENT | RU1-Ref-Pract-SDK-HS1 |\n| B | PRO_CLIENT | RU1-Ref-Pract-SDK-HS2 |","duration":48530,"startTime":"2026-01-11T20:20:03.262230206+01:00[Europe/Berlin]","result":"SUCCESS","precondition":false,"level":1,"children":[{"number":3,"description":"A executes a GET on the resource /devices","duration":79,"startTime":"2026-01-11T20:20:03.264790246+01:00[Europe/Berlin]","result":"SUCCESS","precondition":false,"level":2,"children":[{"number":4,"description":"GET http://RU1-Ref-Pract-SDK-HS1/devices","duration":0,"startTime":"2026-01-11T20:20:03.343948425+01:00[Europe/Berlin]","result":"SUCCESS","restQuery":{"method":"GET","path":"http://RU1-Ref-Pract-SDK-HS1/devices","content":"","contentType":"application/json","requestHeaders":"Transaction-Id\u003d@TCID:TIM_V2_BASIS_AF_11X0123/9a5ac82f-fec9-4de2-a74f-3c51b2bf82c6\n\t\t\t\tAccept\u003d*/*\n\t\t\t\tContent-Type\u003dapplication/json","requestCookies":"","responseHeaders":"Date: Sun, 11 Jan 2026 19:20:03 GMT\nContent-Type: application/json\nContent-Length: 301\nConnection: keep-alive\nStrict-Transport-Security: max-age\u003d31536000; includeSubDomains","responseCookies":"","responseBody":"{\n    \"devices\": [\n        {\n            \"deviceId\": 1,\n            \"deviceName\": \"device-1\",\n            \"deviceStatus\": \"free\",\n            \"claimerName\": \"\",\n            \"claimedUntil\": \"\"\n        },\n        {\n            \"deviceId\": 3,\n            \"deviceName\": \"device-3\",\n            \"deviceStatus\": \"free\",\n            \"claimerName\": \"\",\n            \"claimedUntil\": \"\"\n        },\n        {\n            \"deviceId\": 2,\n            \"deviceName\": \"device-2\",\n            \"deviceStatus\": \"free\",\n            \"claimerName\": \"\",\n            \"claimedUntil\": \"\"\n        }\n    ]\n}","statusCode":200},"precondition":false,"level":3}]},{"number":5,"description":"A executes a POST on the resource /devices/{deviceId}/claim","duration":76,"startTime":"2026-01-11T20:20:03.347623795+01:00[Europe/Berlin]","result":"SUCCESS","precondition":false,"level":2,"children":[{"number":6,"description":"POST http://RU1-Ref-Pract-SDK-HS1/devices/1/claim","duration":0,"startTime":"2026-01-11T20:20:03.424218204+01:00[Europe/Berlin]","result":"SUCCESS","restQuery":{"method":"POST","path":"http://RU1-Ref-Pract-SDK-HS1/devices/1/claim","content":"{\n    \"claimerName\": \"no configured cert found\",\n    \"claimFor\": 600\n}","contentType":"application/json","requestHeaders":"Accept\u003dapplication/json\n\t\t\t\tTransaction-Id\u003d@TCID:TIM_V2_BASIS_AF_11X0123/9a5ac82f-fec9-4de2-a74f-3c51b2bf82c6\n\t\t\t\tContent-Type\u003dapplication/json","requestCookies":"","responseHeaders":"Date: Sun, 11 Jan 2026 19:20:03 GMT\nContent-Type: application/json\nContent-Length: 152\nConnection: keep-alive\nStrict-Transport-Security: max-age\u003d31536000; includeSubDomains","responseCookies":"","responseBody":"{\n    \"deviceId\": 1,\n    \"deviceName\": \"device-1\",\n    \"deviceStatus\": \"claimed\",\n    \"claimerName\": \"no configured cert found\",\n    \"claimedUntil\": \"2026-01-11T19:30:03.415867746Z\"\n}","statusCode":200},"precondition":false,"level":3}]},{"number":7,"description":"A executes a GET on the resource /","duration":80,"startTime":"2026-01-11T20:20:03.437268203+01:00[Europe/Berlin]","result":"SUCCESS","precondition":false,"level":2,"children":[{"number":8,"description":"GET http://RU1-Ref-Pract-SDK-HS1/","duration":0,"startTime":"2026-01-11T20:20:03.517710972+01:00[Europe/Berlin]","result":"SUCCESS","restQuery":{"method":"GET","path":"http://RU1-Ref-Pract-SDK-HS1/","content":"","contentType":"application/json","requestHeaders":"Transaction-Id\u003d@TCID:TIM_V2_BASIS_AF_11X0123/9a5ac82f-fec9-4de2-a74f-3c51b2bf82c6\n\t\t\t\tAccept\u003d*/*\n\t\t\t\tContent-Type\u003dapplication/json","requestCookies":"","responseHeaders":"Date: Sun, 11 Jan 2026 19:20:03 GMT\nContent-Type: application/json\nContent-Length: 588\nConnection: keep-alive\nStrict-Transport-Security: max-age\u003d31536000; includeSubDomains","responseCookies":"","responseBody":"{\n    \"title\": \"Timmy test-driver client\",\n    \"description\": \"TIM test-driver based on trixnity-messenger SDK\",\n    \"homeserver\": \"https://1e6a534d-c4b7-46c4-83d1-4f56e63b6367.ru.timref.akquinet.nx2.dev\",\n    \"contact\": {\n        \"name\": \"Michael Thiele\",\n        \"url\": \"https://timmy-messenger.de\",\n        \"email\": \"michael.thiele@connect2x.de\"\n    },\n    \"clientInfo\": {\n        \"name\": \"Timmy test-driver client\",\n        \"version\": \"0.8.8\",\n        \"osInfo\": {\n            \"operatingSystem\": \"Linux\"\n        },\n        \"canAdministrateFhirPractitioner\": true,\n        \"canSendMessages\": true,\n        \"isInsurance\": false,\n        \"isPro\": true\n    },\n    \"fachdienstInfo\": {\n        \"name\": \"Timmy Fachdienst\",\n        \"version\": \"0.0.1\"\n    },\n    \"testDriverVersion\": \"0.14.15\"\n}","statusCode":200},"precondition":false,"level":3}]},{"number":9,"description":"A login task","duration":24012,"startTime":"2026-01-11T20:20:03.521365702+01:00[Europe/Berlin]","result":"SUCCESS","precondition":false,"level":2,"children":[{"number":10,"description":"A executes a POST on the resource /devices/{deviceId}/login","duration":24007,"startTime":"2026-01-11T20:20:03.522566042+01:00[Europe/Berlin]","result":"SUCCESS","precondition":false,"level":3,"children":[{"number":11,"description":"POST http://RU1-Ref-Pract-SDK-HS1/devices/1/login","duration":0,"startTime":"2026-01-11T20:20:27.530318172+01:00[Europe/Berlin]","result":"SUCCESS","restQuery":{"method":"POST","path":"http://RU1-Ref-Pract-SDK-HS1/devices/1/login","content":"","contentType":"application/json","requestHeaders":"Transaction-Id\u003d@TCID:TIM_V2_BASIS_AF_11X0123/9a5ac82f-fec9-4de2-a74f-3c51b2bf82c6\n\t\t\t\tAccept\u003d*/*\n\t\t\t\tContent-Type\u003dapplication/json","requestCookies":"","responseHeaders":"Date: Sun, 11 Jan 2026 19:20:27 GMT\nContent-Type: application/json\nContent-Length: 303\nConnection: keep-alive\nStrict-Transport-Security: max-age\u003d31536000; includeSubDomains","responseCookies":"","responseBody":"{\n    \"mxid\": \"@tst_generated_qgskfbbjgh:1e6a534d-c4b7-46c4-83d1-4f56e63b6367.ru.timref.akquinet.nx2.dev\",\n    \"accessToken\": \"syt_dHN0X2dlbmVyYXRlZF9xZ3NrZmJiamdo_MoyuKnsmupCyaOpyadCB_3Qu0Te\",\n    \"username\": \"tst_generated_qgskfbbjgh\",\n    \"password\": \"4d52910b-b14d-48e2-8330-7e53d782d4ad\",\n    \"displayName\": \"Cesare, Luca Graf\"\n}","statusCode":200},"precondition":false,"level":4}]}]},{"number":12,"description":"B executes a GET on the resource /devices","duration":75,"startTime":"2026-01-11T20:20:27.536027552+01:00[Europe/Berlin]","result":"SUCCESS","precondition":false,"level":2,"children":[{"number":13,"description":"GET http://RU1-Ref-Pract-SDK-HS2/devices","duration":0,"startTime":"2026-01-11T20:20:27.611100801+01:00[Europe/Berlin]","result":"SUCCESS","restQuery":{"method":"GET","path":"http://RU1-Ref-Pract-SDK-HS2/devices","content":"","contentType":"application/json","requestHeaders":"Transaction-Id\u003d@TCID:TIM_V2_BASIS_AF_11X0123/9a5ac82f-fec9-4de2-a74f-3c51b2bf82c6\n\t\t\t\tAccept\u003d*/*\n\t\t\t\tContent-Type\u003dapplication/json","requestCookies":"","responseHeaders":"Date: Sun, 11 Jan 2026 19:20:27 GMT\nContent-Type: application/json\nContent-Length: 301\nConnection: keep-alive\nStrict-Transport-Security: max-age\u003d31536000; includeSubDomains","responseCookies":"","responseBody":"{\n    \"devices\": [\n        {\n            \"deviceId\": 3,\n            \"deviceName\": \"device-3\",\n            \"deviceStatus\": \"free\",\n            \"claimerName\": \"\",\n            \"claimedUntil\": \"\"\n        },\n        {\n            \"deviceId\": 2,\n            \"deviceName\": \"device-2\",\n            \"deviceStatus\": \"free\",\n            \"claimerName\": \"\",\n            \"claimedUntil\": \"\"\n        },\n        {\n            \"deviceId\": 1,\n            \"deviceName\": \"device-1\",\n            \"deviceStatus\": \"free\",\n            \"claimerName\": \"\",\n            \"claimedUntil\": \"\"\n        }\n    ]\n}","statusCode":200},"precondition":false,"level":3}]},{"number":14,"description":"B executes a POST on the resource /devices/{deviceId}/claim","duration":79,"startTime":"2026-01-11T20:20:27.615602291+01:00[Europe/Berlin]","result":"SUCCESS","precondition":false,"level":2,"children":[{"number":15,"description":"POST http://RU1-Ref-Pract-SDK-HS2/devices/3/claim","duration":0,"startTime":"2026-01-11T20:20:27.695086710+01:00[Europe/Berlin]","result":"SUCCESS","restQuery":{"method":"POST","path":"http://RU1-Ref-Pract-SDK-HS2/devices/3/claim","content":"{\n    \"claimerName\": \"no configured cert found\",\n    \"claimFor\": 600\n}","contentType":"application/json","requestHeaders":"Accept\u003dapplication/json\n\t\t\t\tTransaction-Id\u003d@TCID:TIM_V2_BASIS_AF_11X0123/9a5ac82f-fec9-4de2-a74f-3c51b2bf82c6\n\t\t\t\tContent-Type\u003dapplication/json","requestCookies":"","responseHeaders":"Date: Sun, 11 Jan 2026 19:20:27 GMT\nContent-Type: application/json\nContent-Length: 152\nConnection: keep-alive\nStrict-Transport-Security: max-age\u003d31536000; includeSubDomains","responseCookies":"","responseBody":"{\n    \"deviceId\": 3,\n    \"deviceName\": \"device-3\",\n    \"deviceStatus\": \"claimed\",\n    \"claimerName\": \"no configured cert found\",\n    \"claimedUntil\": \"2026-01-11T19:30:27.686773479Z\"\n}","statusCode":200},"precondition":false,"level":3}]},{"number":16,"description":"B executes a GET on the resource /","duration":80,"startTime":"2026-01-11T20:20:27.705837529+01:00[Europe/Berlin]","result":"SUCCESS","precondition":false,"level":2,"children":[{"number":17,"description":"GET http://RU1-Ref-Pract-SDK-HS2/","duration":0,"startTime":"2026-01-11T20:20:27.786010768+01:00[Europe/Berlin]","result":"SUCCESS","restQuery":{"method":"GET","path":"http://RU1-Ref-Pract-SDK-HS2/","content":"","contentType":"application/json","requestHeaders":"Transaction-Id\u003d@TCID:TIM_V2_BASIS_AF_11X0123/9a5ac82f-fec9-4de2-a74f-3c51b2bf82c6\n\t\t\t\tAccept\u003d*/*\n\t\t\t\tContent-Type\u003dapplication/json","requestCookies":"","responseHeaders":"Date: Sun, 11 Jan 2026 19:20:27 GMT\nContent-Type: application/json\nContent-Length: 588\nConnection: keep-alive\nStrict-Transport-Security: max-age\u003d31536000; includeSubDomains","responseCookies":"","responseBody":"{\n    \"title\": \"Timmy test-driver client\",\n    \"description\": \"TIM test-driver based on trixnity-messenger SDK\",\n    \"homeserver\": \"https://0ed5d2be-d54d-4b01-b98a-10f3465ca7b5.ru.timref.akquinet.nx2.dev\",\n    \"contact\": {\n        \"name\": \"Michael Thiele\",\n        \"url\": \"https://timmy-messenger.de\",\n        \"email\": \"michael.thiele@connect2x.de\"\n    },\n    \"clientInfo\": {\n        \"name\": \"Timmy test-driver client\",\n        \"version\": \"0.8.8\",\n        \"osInfo\": {\n            \"operatingSystem\": \"Linux\"\n        },\n        \"canAdministrateFhirPractitioner\": true,\n        \"canSendMessages\": true,\n        \"isInsurance\": false,\n        \"isPro\": true\n    },\n    \"fachdienstInfo\": {\n        \"name\": \"Timmy Fachdienst\",\n        \"version\": \"0.0.1\"\n    },\n    \"testDriverVersion\": \"0.14.15\"\n}","statusCode":200},"precondition":false,"level":3}]},{"number":18,"description":"B login task","duration":23758,"startTime":"2026-01-11T20:20:27.789703808+01:00[Europe/Berlin]","result":"SUCCESS","reportData":[{"title":"cURL   0","contents":"curl -v -H \"Transaction-Id: @TCID:TIM_V2_BASIS_AF_11X0122/5f3450e9-0e46-4d39-b4a3-714229b6e0b3\" -H \"Accept: */*\" -H \"Content-Type: application/json\" -X GET \"http://RU1-Ref-Pract-SDK-HS2/devices/1/rooms\" ","isEvidence":false,"id":"report-data-4f63f8bf-4e0e-498e-8d45-50418be99010"},{"title":"cURL   1","contents":"curl -v -H \"Transaction-Id: @TCID:TIM_V2_BASIS_AF_11X0122/5f3450e9-0e46-4d39-b4a3-714229b6e0b3\" -H \"Accept: */*\" -H \"Content-Type: application/json\" -X POST \"http://RU1-Ref-Pract-SDK-HS2/devices/1/rooms/%21smVBwYSMTvGvXoaOOg%3A0ed5d2be-d54d-4b01-b98a-10f3465ca7b5.ru.timref.akquinet.nx2.dev/leave\" ","isEvidence":false,"id":"report-data-7361209f-2b67-49d9-b718-7ab3799e1b97"},{"title":"cURL   2","contents":"curl -v -H \"Transaction-Id: @TCID:TIM_V2_BASIS_AF_11X0122/5f3450e9-0e46-4d39-b4a3-714229b6e0b3\" -H \"Accept: */*\" -H \"Content-Type: application/json\" -X DELETE \"http://RU1-Ref-Pract-SDK-HS2/devices/1/rooms/%21smVBwYSMTvGvXoaOOg%3A0ed5d2be-d54d-4b01-b98a-10f3465ca7b5.ru.timref.akquinet.nx2.dev\" ","isEvidence":false,"id":"report-data-e4234303-d388-4409-b2ff-6a1bca77daf9"},{"title":"cURL   3","contents":"curl -v -H \"Transaction-Id: @TCID:TIM_V2_BASIS_AF_11X0122/5f3450e9-0e46-4d39-b4a3-714229b6e0b3\" -H \"Accept: */*\" -H \"Content-Type: application/json\" -X POST \"http://RU1-Ref-Pract-SDK-HS2/devices/1/logout\" ","isEvidence":false,"id":"report-data-ff66bd4c-3ede-4550-89cc-ffac13aee09a"},{"title":"cURL   4","contents":"curl -v -H \"Transaction-Id: @TCID:TIM_V2_BASIS_AF_11X0122/5f3450e9-0e46-4d39-b4a3-714229b6e0b3\" -H \"Accept: */*\" -H \"Content-Type: application/json\" -X POST \"http://RU1-Ref-Pract-SDK-HS2/devices/1/unclaim\" ","isEvidence":false,"id":"report-data-b8c40919-b314-4b31-9ced-dac6e1d0d2d8"},{"title":"cURL   5","contents":"curl -v -H \"Transaction-Id: @TCID:TIM_V2_BASIS_AF_11X0122/5f3450e9-0e46-4d39-b4a3-714229b6e0b3\" -H \"Accept: */*\" -H \"Content-Type: application/json\" -X GET \"http://RU1-Ref-Pract-SDK-HS1/devices/2/rooms\" ","isEvidence":false,"id":"report-data-fe9978ac-d104-4566-affe-06572328d1a1"},{"title":"cURL   6","contents":"curl -v -H \"Transaction-Id: @TCID:TIM_V2_BASIS_AF_11X0122/5f3450e9-0e46-4d39-b4a3-714229b6e0b3\" -H \"Accept: */*\" -H \"Content-Type: application/json\" -X POST \"http://RU1-Ref-Pract-SDK-HS1/devices/2/rooms/%21smVBwYSMTvGvXoaOOg%3A0ed5d2be-d54d-4b01-b98a-10f3465ca7b5.ru.timref.akquinet.nx2.dev/leave\" ","isEvidence":false,"id":"report-data-80aca1ad-1d91-427e-9132-cb31ad43b066"},{"title":"cURL   7","contents":"curl -v -H \"Transaction-Id: @TCID:TIM_V2_BASIS_AF_11X0122/5f3450e9-0e46-4d39-b4a3-714229b6e0b3\" -H \"Accept: */*\" -H \"Content-Type: application/json\" -X DELETE \"http://RU1-Ref-Pract-SDK-HS1/devices/2/rooms/%21smVBwYSMTvGvXoaOOg%3A0ed5d2be-d54d-4b01-b98a-10f3465ca7b5.ru.timref.akquinet.nx2.dev\" ","isEvidence":false,"id":"report-data-37217bbc-f060-4239-9ecf-c07f6ae34ea5"},{"title":"cURL   8","contents":"curl -v -H \"Transaction-Id: @TCID:TIM_V2_BASIS_AF_11X0122/5f3450e9-0e46-4d39-b4a3-714229b6e0b3\" -H \"Accept: */*\" -H \"Content-Type: application/json\" -X POST \"http://RU1-Ref-Pract-SDK-HS1/devices/2/logout\" ","isEvidence":false,"id":"report-data-437b0fbb-f5e0-4812-b454-2e8012d2b923"},{"title":"cURL   9","contents":"curl -v -H \"Transaction-Id: @TCID:TIM_V2_BASIS_AF_11X0122/5f3450e9-0e46-4d39-b4a3-714229b6e0b3\" -H \"Accept: */*\" -H \"Content-Type: application/json\" -X POST \"http://RU1-Ref-Pract-SDK-HS1/devices/2/unclaim\" ","isEvidence":false,"id":"report-data-13c28849-959f-4d4a-934c-da675a8d3453"},{"title":"cURL  10","contents":"curl -v -H \"Transaction-Id: @TCID:TIM_V2_BASIS_AF_11X0123/9a5ac82f-fec9-4de2-a74f-3c51b2bf82c6\" -H \"Accept: */*\" -H \"Content-Type: application/json\" -X GET \"http://RU1-Ref-Pract-SDK-HS1/devices\" ","isEvidence":false,"id":"report-data-effdb882-6601-4c10-9db8-5a72a031018c"},{"title":"cURL  11","contents":"curl -v -H \"Accept: application/json\" -H \"Transaction-Id: @TCID:TIM_V2_BASIS_AF_11X0123/9a5ac82f-fec9-4de2-a74f-3c51b2bf82c6\" -H \"Content-Type: application/json\" -X POST \"http://RU1-Ref-Pract-SDK-HS1/devices/1/claim\" ","isEvidence":false,"id":"report-data-d3f49eb4-0cb9-47b7-ae57-016a7a1e4f76"},{"title":"cURL  12","contents":"curl -v -H \"Transaction-Id: @TCID:TIM_V2_BASIS_AF_11X0123/9a5ac82f-fec9-4de2-a74f-3c51b2bf82c6\" -H \"Accept: */*\" -H \"Content-Type: application/json\" -X GET \"http://RU1-Ref-Pract-SDK-HS1/\" ","isEvidence":false,"id":"report-data-3a242cfe-ff28-4134-8e1b-b56d7df38dcc"},{"title":"cURL  13","contents":"curl -v -H \"Transaction-Id: @TCID:TIM_V2_BASIS_AF_11X0123/9a5ac82f-fec9-4de2-a74f-3c51b2bf82c6\" -H \"Accept: */*\" -H \"Content-Type: application/json\" -X POST \"http://RU1-Ref-Pract-SDK-HS1/devices/1/login\" ","isEvidence":false,"id":"report-data-acc6e904-16c8-46a0-b333-e0342295e0c0"},{"title":"cURL  14","contents":"curl -v -H \"Transaction-Id: @TCID:TIM_V2_BASIS_AF_11X0123/9a5ac82f-fec9-4de2-a74f-3c51b2bf82c6\" -H \"Accept: */*\" -H \"Content-Type: application/json\" -X GET \"http://RU1-Ref-Pract-SDK-HS2/devices\" ","isEvidence":false,"id":"report-data-e74a7d0a-6915-46fe-88ae-f65a2ebd69a4"},{"title":"cURL  15","contents":"curl -v -H \"Accept: application/json\" -H \"Transaction-Id: @TCID:TIM_V2_BASIS_AF_11X0123/9a5ac82f-fec9-4de2-a74f-3c51b2bf82c6\" -H \"Content-Type: application/json\" -X POST \"http://RU1-Ref-Pract-SDK-HS2/devices/3/claim\" ","isEvidence":false,"id":"report-data-1092beaf-6111-4926-97b0-0fe25c80138e"},{"title":"cURL  16","contents":"curl -v -H \"Transaction-Id: @TCID:TIM_V2_BASIS_AF_11X0123/9a5ac82f-fec9-4de2-a74f-3c51b2bf82c6\" -H \"Accept: */*\" -H \"Content-Type: application/json\" -X GET \"http://RU1-Ref-Pract-SDK-HS2/\" ","isEvidence":false,"id":"report-data-5d27e2b5-838f-4721-9758-908c07eea638"},{"title":"cURL  17","contents":"curl -v -H \"Transaction-Id: @TCID:TIM_V2_BASIS_AF_11X0123/9a5ac82f-fec9-4de2-a74f-3c51b2bf82c6\" -H \"Accept: */*\" -H \"Content-Type: application/json\" -X POST \"http://RU1-Ref-Pract-SDK-HS2/devices/3/login\" ","isEvidence":false,"id":"report-data-80781e2d-672c-475f-94d5-4a5f1a285a23"}],"precondition":false,"level":2,"children":[{"number":19,"description":"B executes a POST on the resource /devices/{deviceId}/login","duration":23750,"startTime":"2026-01-11T20:20:27.791018798+01:00[Europe/Berlin]","result":"SUCCESS","precondition":false,"level":3,"children":[{"number":20,"description":"POST http://RU1-Ref-Pract-SDK-HS2/devices/3/login","duration":0,"startTime":"2026-01-11T20:20:51.541668740+01:00[Europe/Berlin]","result":"SUCCESS","restQuery":{"method":"POST","path":"http://RU1-Ref-Pract-SDK-HS2/devices/3/login","content":"","contentType":"application/json","requestHeaders":"Transaction-Id\u003d@TCID:TIM_V2_BASIS_AF_11X0123/9a5ac82f-fec9-4de2-a74f-3c51b2bf82c6\n\t\t\t\tAccept\u003d*/*\n\t\t\t\tContent-Type\u003dapplication/json","requestCookies":"","responseHeaders":"Date: Sun, 11 Jan 2026 19:20:51 GMT\nContent-Type: application/json\nContent-Length: 307\nConnection: keep-alive\nStrict-Transport-Security: max-age\u003d31536000; includeSubDomains","responseCookies":"","responseBody":"{\n    \"mxid\": \"@tst_generated_aafdnvkgdg:0ed5d2be-d54d-4b01-b98a-10f3465ca7b5.ru.timref.akquinet.nx2.dev\",\n    \"accessToken\": \"syt_dHN0X2dlbmVyYXRlZF9hYWZkbnZrZ2Rn_YVgaERMFwQyJvNREWgKO_2eTHiV\",\n    \"username\": \"tst_generated_aafdnvkgdg\",\n    \"password\": \"92608f39-9465-40ea-ac8f-113e139893c8\",\n    \"displayName\": \"Nullmayr, Gernot Graf\"\n}","statusCode":200},"precondition":false,"level":4}]}]}]},{"number":21,"description":"Und \"A\", \"B\" setzen den eigenen Authorization Mode auf \"AllowAll\"","duration":4402,"startTime":"2026-01-11T20:20:51.792790516+01:00[Europe/Berlin]","result":"SUCCESS","precondition":false,"level":1,"children":[{"number":22,"description":"A executes a POST on the resource /devices/{deviceId}/authorizationMode","duration":2114,"startTime":"2026-01-11T20:20:51.796613236+01:00[Europe/Berlin]","result":"SUCCESS","precondition":false,"level":2,"children":[{"number":23,"description":"POST http://RU1-Ref-Pract-SDK-HS1/devices/1/authorizationMode","duration":0,"startTime":"2026-01-11T20:20:53.910997282+01:00[Europe/Berlin]","result":"SUCCESS","restQuery":{"method":"POST","path":"http://RU1-Ref-Pract-SDK-HS1/devices/1/authorizationMode","content":"\"AllowAll\"","contentType":"application/json","requestHeaders":"Transaction-Id\u003d@TCID:TIM_V2_BASIS_AF_11X0123/9a5ac82f-fec9-4de2-a74f-3c51b2bf82c6\n\t\t\t\tAccept\u003d*/*\n\t\t\t\tContent-Type\u003dapplication/json","requestCookies":"","responseHeaders":"Date: Sun, 11 Jan 2026 19:20:53 GMT\nContent-Type: application/json\nContent-Length: 10\nConnection: keep-alive\nStrict-Transport-Security: max-age\u003d31536000; includeSubDomains","responseCookies":"","responseBody":"\"AllowAll\"","statusCode":200},"precondition":false,"level":3}]},{"number":24,"description":"B executes a POST on the resource /devices/{deviceId}/authorizationMode","duration":2078,"startTime":"2026-01-11T20:20:53.913958151+01:00[Europe/Berlin]","result":"SUCCESS","reportData":[{"title":"cURL   0","contents":"curl -v -H \"Transaction-Id: @TCID:TIM_V2_BASIS_AF_11X0123/9a5ac82f-fec9-4de2-a74f-3c51b2bf82c6\" -H \"Accept: */*\" -H \"Content-Type: application/json\" -X POST \"http://RU1-Ref-Pract-SDK-HS1/devices/1/authorizationMode\" ","isEvidence":false,"id":"report-data-8e4a5e8f-ea5b-4f87-a1f6-fa318776e8bb"},{"title":"cURL   1","contents":"curl -v -H \"Transaction-Id: @TCID:TIM_V2_BASIS_AF_11X0123/9a5ac82f-fec9-4de2-a74f-3c51b2bf82c6\" -H \"Accept: */*\" -H \"Content-Type: application/json\" -X POST \"http://RU1-Ref-Pract-SDK-HS2/devices/3/authorizationMode\" ","isEvidence":false,"id":"report-data-abba7220-33cf-4edd-a233-b04243b71c12"}],"precondition":false,"level":2,"children":[{"number":25,"description":"POST http://RU1-Ref-Pract-SDK-HS2/devices/3/authorizationMode","duration":0,"startTime":"2026-01-11T20:20:55.992295278+01:00[Europe/Berlin]","result":"SUCCESS","restQuery":{"method":"POST","path":"http://RU1-Ref-Pract-SDK-HS2/devices/3/authorizationMode","content":"\"AllowAll\"","contentType":"application/json","requestHeaders":"Transaction-Id\u003d@TCID:TIM_V2_BASIS_AF_11X0123/9a5ac82f-fec9-4de2-a74f-3c51b2bf82c6\n\t\t\t\tAccept\u003d*/*\n\t\t\t\tContent-Type\u003dapplication/json","requestCookies":"","responseHeaders":"Date: Sun, 11 Jan 2026 19:20:55 GMT\nContent-Type: application/json\nContent-Length: 10\nConnection: keep-alive\nStrict-Transport-Security: max-age\u003d31536000; includeSubDomains","responseCookies":"","responseBody":"\"AllowAll\"","statusCode":200},"precondition":false,"level":3}]}]},{"number":26,"description":"Wenn \"A\" sendet ein Attachment \"video.mov\" direkt an \"B\" als \"m.video\"","duration":11970,"startTime":"2026-01-11T20:20:56.195678394+01:00[Europe/Berlin]","result":"SUCCESS","precondition":false,"level":1,"children":[{"number":27,"description":"A upload media task","duration":276,"startTime":"2026-01-11T20:20:56.198297194+01:00[Europe/Berlin]","result":"SUCCESS","precondition":false,"level":2,"children":[{"number":28,"description":"A executes a POST on the resource /devices/{deviceId}/media","duration":273,"startTime":"2026-01-11T20:20:56.199770454+01:00[Europe/Berlin]","result":"SUCCESS","precondition":false,"level":3,"children":[{"number":29,"description":"POST http://RU1-Ref-Pract-SDK-HS1/devices/1/media","duration":0,"startTime":"2026-01-11T20:20:56.473357150+01:00[Europe/Berlin]","result":"SUCCESS","restQuery":{"method":"POST","path":"http://RU1-Ref-Pract-SDK-HS1/devices/1/media","content":"[Body content omitted due to binary or size constraints]","contentType":"application/octet-stream","requestHeaders":"Transaction-Id\u003d@TCID:TIM_V2_BASIS_AF_11X0123/9a5ac82f-fec9-4de2-a74f-3c51b2bf82c6\n\t\t\t\tAccept\u003d*/*\n\t\t\t\tContent-Type\u003dapplication/octet-stream; charset\u003dISO-8859-1","requestCookies":"","responseHeaders":"Date: Sun, 11 Jan 2026 19:20:56 GMT\nContent-Type: application/json\nContent-Length: 49\nConnection: keep-alive\nStrict-Transport-Security: max-age\u003d31536000; includeSubDomains","responseCookies":"","responseBody":"{\n    \"fileId\": \"96b1eb3b-3fe8-4409-bb76-9b01b99cb292\"\n}","statusCode":201},"precondition":false,"level":4}]}]},{"number":30,"description":"A executes a POST on the resource /devices/{deviceId}/sendMessage","duration":11304,"startTime":"2026-01-11T20:20:56.477000480+01:00[Europe/Berlin]","result":"SUCCESS","precondition":false,"level":2,"children":[{"number":31,"description":"POST http://RU1-Ref-Pract-SDK-HS1/devices/1/sendMessage","duration":0,"startTime":"2026-01-11T20:21:07.781421245+01:00[Europe/Berlin]","result":"SUCCESS","restQuery":{"method":"POST","path":"http://RU1-Ref-Pract-SDK-HS1/devices/1/sendMessage","content":"{\n    \"body\": \"video.mov\",\n    \"msgtype\": \"m.video\",\n    \"fileId\": \"96b1eb3b-3fe8-4409-bb76-9b01b99cb292\",\n    \"info\": {\n        \"mimetype\": \"video/quicktime\",\n        \"size\": 394733\n    },\n    \"format\": null,\n    \"formatted_body\": null,\n    \"filename\": null,\n    \"file\": null,\n    \"geo_uri\": null,\n    \"toAccount\": \"@tst_generated_aafdnvkgdg:0ed5d2be-d54d-4b01-b98a-10f3465ca7b5.ru.timref.akquinet.nx2.dev\"\n}","contentType":"application/json","requestHeaders":"Transaction-Id\u003d@TCID:TIM_V2_BASIS_AF_11X0123/9a5ac82f-fec9-4de2-a74f-3c51b2bf82c6\n\t\t\t\tAccept\u003d*/*\n\t\t\t\tContent-Type\u003dapplication/json","requestCookies":"","responseHeaders":"Date: Sun, 11 Jan 2026 19:21:07 GMT\nContent-Type: application/json\nContent-Length: 808\nConnection: keep-alive\nStrict-Transport-Security: max-age\u003d31536000; includeSubDomains","responseCookies":"","responseBody":"{\n    \"body\": \"video.mov\",\n    \"msgtype\": \"m.video\",\n    \"fileId\": \"96b1eb3b-3fe8-4409-bb76-9b01b99cb292\",\n    \"info\": {\n        \"mimetype\": \"video/quicktime\",\n        \"size\": 394733\n    },\n    \"file\": {\n        \"url\": \"mxc://1e6a534d-c4b7-46c4-83d1-4f56e63b6367.ru.timref.akquinet.nx2.dev/FlBFDTTviUyaXMcPonseqHGs\",\n        \"key\": {\n            \"k\": \"AR-M-1ATwcOC-0eIDTM1LNuJwPo4_GQNwHuO_-bUsCo\",\n            \"kty\": \"oct\",\n            \"key_ops\": [\n                \"encrypt\",\n                \"decrypt\"\n            ],\n            \"alg\": \"A256CTR\",\n            \"ext\": true\n        },\n        \"iv\": \"Wug8puakqJQAAAAAAAAAAA\",\n        \"hashes\": {\n            \"sha256\": \"gpNiz9mK8+FUEFjY1R6/UioVpxBAW9rNU2XTceJ8vRA\"\n        },\n        \"v\": \"v2\"\n    },\n    \"event_id\": \"$gsEYDo_5rAnnUXJOiENj1pWGikQKBiACllHOO-UMsk8\",\n    \"type\": \"m.room.message\",\n    \"messageId\": \"$gsEYDo_5rAnnUXJOiENj1pWGikQKBiACllHOO-UMsk8\",\n    \"timestamp\": \"2026-01-11T19:21:02.678Z\",\n    \"lastUpdated\": \"2026-01-11T19:21:02.678Z\",\n    \"author\": \"@tst_generated_qgskfbbjgh:1e6a534d-c4b7-46c4-83d1-4f56e63b6367.ru.timref.akquinet.nx2.dev\"\n}","statusCode":200},"precondition":false,"level":3}]},{"number":32,"description":"A executes a GET on the resource /devices/{deviceId}/rooms","duration":50,"startTime":"2026-01-11T20:21:07.795724975+01:00[Europe/Berlin]","result":"SUCCESS","precondition":false,"level":2,"children":[{"number":33,"description":"GET http://RU1-Ref-Pract-SDK-HS1/devices/1/rooms","duration":0,"startTime":"2026-01-11T20:21:07.846129454+01:00[Europe/Berlin]","result":"SUCCESS","restQuery":{"method":"GET","path":"http://RU1-Ref-Pract-SDK-HS1/devices/1/rooms","content":"","contentType":"application/json","requestHeaders":"Transaction-Id\u003d@TCID:TIM_V2_BASIS_AF_11X0123/9a5ac82f-fec9-4de2-a74f-3c51b2bf82c6\n\t\t\t\tAccept\u003d*/*\n\t\t\t\tContent-Type\u003dapplication/json","requestCookies":"","responseHeaders":"Date: Sun, 11 Jan 2026 19:21:07 GMT\nContent-Type: application/json\nContent-Length: 523\nConnection: keep-alive\nStrict-Transport-Security: max-age\u003d31536000; includeSubDomains","responseCookies":"","responseBody":"[\n    {\n        \"name\": \"room-!QSeEXFhAqJRWGPkVab:1e6a534d-c4b7-46c4-83d1-4f56e63b6367.ru.timref.akquinet.nx2.dev\",\n        \"roomAccess\": \"private\",\n        \"isEncrypted\": true,\n        \"roomId\": \"!QSeEXFhAqJRWGPkVab:1e6a534d-c4b7-46c4-83d1-4f56e63b6367.ru.timref.akquinet.nx2.dev\",\n        \"members\": [\n            {\n                \"mxid\": \"@tst_generated_qgskfbbjgh:1e6a534d-c4b7-46c4-83d1-4f56e63b6367.ru.timref.akquinet.nx2.dev\",\n                \"membershipState\": \"join\"\n            },\n            {\n                \"mxid\": \"@tst_generated_aafdnvkgdg:0ed5d2be-d54d-4b01-b98a-10f3465ca7b5.ru.timref.akquinet.nx2.dev\",\n                \"membershipState\": \"invite\"\n            }\n        ],\n        \"roomVersion\": \"10\"\n    }\n]","statusCode":200},"precondition":false,"level":3}]},{"number":34,"description":"A executes a GET on the resource /devices/{deviceId}/rooms","duration":84,"startTime":"2026-01-11T20:21:07.850178454+01:00[Europe/Berlin]","result":"SUCCESS","reportData":[{"title":"cURL   0","contents":"curl -v -H \"Transaction-Id: @TCID:TIM_V2_BASIS_AF_11X0123/9a5ac82f-fec9-4de2-a74f-3c51b2bf82c6\" -H \"Accept: */*\" -H \"Content-Type: application/octet-stream; charset\u003dISO-8859-1\" -X POST \"http://RU1-Ref-Pract-SDK-HS1/devices/1/media\" ","isEvidence":false,"id":"report-data-26f5f6dc-d59e-4cc2-aeb0-3705600e100c"},{"title":"cURL   1","contents":"curl -v -H \"Transaction-Id: @TCID:TIM_V2_BASIS_AF_11X0123/9a5ac82f-fec9-4de2-a74f-3c51b2bf82c6\" -H \"Accept: */*\" -H \"Content-Type: application/json\" -X POST \"http://RU1-Ref-Pract-SDK-HS1/devices/1/sendMessage\" ","isEvidence":false,"id":"report-data-ae42f64c-6188-45ae-b288-d7265274e35e"},{"title":"cURL   2","contents":"curl -v -H \"Transaction-Id: @TCID:TIM_V2_BASIS_AF_11X0123/9a5ac82f-fec9-4de2-a74f-3c51b2bf82c6\" -H \"Accept: */*\" -H \"Content-Type: application/json\" -X GET \"http://RU1-Ref-Pract-SDK-HS1/devices/1/rooms\" ","isEvidence":false,"id":"report-data-2e83af59-834c-47c4-b363-7f8311a4ef48"},{"title":"cURL   3","contents":"curl -v -H \"Transaction-Id: @TCID:TIM_V2_BASIS_AF_11X0123/9a5ac82f-fec9-4de2-a74f-3c51b2bf82c6\" -H \"Accept: */*\" -H \"Content-Type: application/json\" -X GET \"http://RU1-Ref-Pract-SDK-HS1/devices/1/rooms\" ","isEvidence":false,"id":"report-data-42214e64-5c28-43e0-b29b-920904b62d74"}],"precondition":false,"level":2,"children":[{"number":35,"description":"GET http://RU1-Ref-Pract-SDK-HS1/devices/1/rooms","duration":0,"startTime":"2026-01-11T20:21:07.934580862+01:00[Europe/Berlin]","result":"SUCCESS","restQuery":{"method":"GET","path":"http://RU1-Ref-Pract-SDK-HS1/devices/1/rooms","content":"","contentType":"application/json","requestHeaders":"Transaction-Id\u003d@TCID:TIM_V2_BASIS_AF_11X0123/9a5ac82f-fec9-4de2-a74f-3c51b2bf82c6\n\t\t\t\tAccept\u003d*/*\n\t\t\t\tContent-Type\u003dapplication/json","requestCookies":"","responseHeaders":"Date: Sun, 11 Jan 2026 19:21:07 GMT\nContent-Type: application/json\nContent-Length: 523\nConnection: keep-alive\nStrict-Transport-Security: max-age\u003d31536000; includeSubDomains","responseCookies":"","responseBody":"[\n    {\n        \"name\": \"room-!QSeEXFhAqJRWGPkVab:1e6a534d-c4b7-46c4-83d1-4f56e63b6367.ru.timref.akquinet.nx2.dev\",\n        \"roomAccess\": \"private\",\n        \"isEncrypted\": true,\n        \"roomId\": \"!QSeEXFhAqJRWGPkVab:1e6a534d-c4b7-46c4-83d1-4f56e63b6367.ru.timref.akquinet.nx2.dev\",\n        \"members\": [\n            {\n                \"mxid\": \"@tst_generated_qgskfbbjgh:1e6a534d-c4b7-46c4-83d1-4f56e63b6367.ru.timref.akquinet.nx2.dev\",\n                \"membershipState\": \"join\"\n            },\n            {\n                \"mxid\": \"@tst_generated_aafdnvkgdg:0ed5d2be-d54d-4b01-b98a-10f3465ca7b5.ru.timref.akquinet.nx2.dev\",\n                \"membershipState\": \"invite\"\n            }\n        ],\n        \"roomVersion\": \"10\"\n    }\n]","statusCode":200},"precondition":false,"level":3}]}]},{"number":36,"description":"Und \"B\" erhält eine Einladung von \"A\"","duration":286,"startTime":"2026-01-11T20:21:08.166530798+01:00[Europe/Berlin]","result":"SUCCESS","precondition":false,"level":1,"children":[{"number":37,"description":"A executes a GET on the resource /devices/{deviceId}/rooms","duration":78,"startTime":"2026-01-11T20:21:08.169785898+01:00[Europe/Berlin]","result":"SUCCESS","reportData":[{"title":"cURL","contents":"curl -v -H \"Transaction-Id: @TCID:TIM_V2_BASIS_AF_11X0123/9a5ac82f-fec9-4de2-a74f-3c51b2bf82c6\" -H \"Accept: */*\" -H \"Content-Type: application/json\" -X GET \"http://RU1-Ref-Pract-SDK-HS1/devices/1/rooms\" ","isEvidence":false,"id":"report-data-248a48c9-2fe3-4829-a03c-f48d6f43292f"}],"precondition":false,"level":2,"children":[{"number":38,"description":"GET http://RU1-Ref-Pract-SDK-HS1/devices/1/rooms","duration":0,"startTime":"2026-01-11T20:21:08.247957297+01:00[Europe/Berlin]","result":"SUCCESS","restQuery":{"method":"GET","path":"http://RU1-Ref-Pract-SDK-HS1/devices/1/rooms","content":"","contentType":"application/json","requestHeaders":"Transaction-Id\u003d@TCID:TIM_V2_BASIS_AF_11X0123/9a5ac82f-fec9-4de2-a74f-3c51b2bf82c6\n\t\t\t\tAccept\u003d*/*\n\t\t\t\tContent-Type\u003dapplication/json","requestCookies":"","responseHeaders":"Date: Sun, 11 Jan 2026 19:21:08 GMT\nContent-Type: application/json\nContent-Length: 523\nConnection: keep-alive\nStrict-Transport-Security: max-age\u003d31536000; includeSubDomains","responseCookies":"","responseBody":"[\n    {\n        \"name\": \"room-!QSeEXFhAqJRWGPkVab:1e6a534d-c4b7-46c4-83d1-4f56e63b6367.ru.timref.akquinet.nx2.dev\",\n        \"roomAccess\": \"private\",\n        \"isEncrypted\": true,\n        \"roomId\": \"!QSeEXFhAqJRWGPkVab:1e6a534d-c4b7-46c4-83d1-4f56e63b6367.ru.timref.akquinet.nx2.dev\",\n        \"members\": [\n            {\n                \"mxid\": \"@tst_generated_qgskfbbjgh:1e6a534d-c4b7-46c4-83d1-4f56e63b6367.ru.timref.akquinet.nx2.dev\",\n                \"membershipState\": \"join\"\n            },\n            {\n                \"mxid\": \"@tst_generated_aafdnvkgdg:0ed5d2be-d54d-4b01-b98a-10f3465ca7b5.ru.timref.akquinet.nx2.dev\",\n                \"membershipState\": \"invite\"\n            }\n        ],\n        \"roomVersion\": \"10\"\n    }\n]","statusCode":200},"precondition":false,"level":3}]}]},{"number":39,"description":"Und \"B\" bestätigt eine Einladung von \"A\"","duration":3211,"startTime":"2026-01-11T20:21:08.453013054+01:00[Europe/Berlin]","result":"SUCCESS","precondition":false,"level":1,"children":[{"number":40,"description":"A executes a GET on the resource /devices/{deviceId}/rooms","duration":83,"startTime":"2026-01-11T20:21:08.455646564+01:00[Europe/Berlin]","result":"SUCCESS","precondition":false,"level":2,"children":[{"number":41,"description":"GET http://RU1-Ref-Pract-SDK-HS1/devices/1/rooms","duration":0,"startTime":"2026-01-11T20:21:08.538938682+01:00[Europe/Berlin]","result":"SUCCESS","restQuery":{"method":"GET","path":"http://RU1-Ref-Pract-SDK-HS1/devices/1/rooms","content":"","contentType":"application/json","requestHeaders":"Transaction-Id\u003d@TCID:TIM_V2_BASIS_AF_11X0123/9a5ac82f-fec9-4de2-a74f-3c51b2bf82c6\n\t\t\t\tAccept\u003d*/*\n\t\t\t\tContent-Type\u003dapplication/json","requestCookies":"","responseHeaders":"Date: Sun, 11 Jan 2026 19:21:08 GMT\nContent-Type: application/json\nContent-Length: 523\nConnection: keep-alive\nStrict-Transport-Security: max-age\u003d31536000; includeSubDomains","responseCookies":"","responseBody":"[\n    {\n        \"name\": \"room-!QSeEXFhAqJRWGPkVab:1e6a534d-c4b7-46c4-83d1-4f56e63b6367.ru.timref.akquinet.nx2.dev\",\n        \"roomAccess\": \"private\",\n        \"isEncrypted\": true,\n        \"roomId\": \"!QSeEXFhAqJRWGPkVab:1e6a534d-c4b7-46c4-83d1-4f56e63b6367.ru.timref.akquinet.nx2.dev\",\n        \"members\": [\n            {\n                \"mxid\": \"@tst_generated_qgskfbbjgh:1e6a534d-c4b7-46c4-83d1-4f56e63b6367.ru.timref.akquinet.nx2.dev\",\n                \"membershipState\": \"join\"\n            },\n            {\n                \"mxid\": \"@tst_generated_aafdnvkgdg:0ed5d2be-d54d-4b01-b98a-10f3465ca7b5.ru.timref.akquinet.nx2.dev\",\n                \"membershipState\": \"invite\"\n            }\n        ],\n        \"roomVersion\": \"10\"\n    }\n]","statusCode":200},"precondition":false,"level":3}]},{"number":42,"description":"B executes a GET on the resource /devices/{deviceId}/rooms","duration":83,"startTime":"2026-01-11T20:21:08.543143712+01:00[Europe/Berlin]","result":"SUCCESS","precondition":false,"level":2,"children":[{"number":43,"description":"GET http://RU1-Ref-Pract-SDK-HS2/devices/3/rooms","duration":0,"startTime":"2026-01-11T20:21:08.626259921+01:00[Europe/Berlin]","result":"SUCCESS","restQuery":{"method":"GET","path":"http://RU1-Ref-Pract-SDK-HS2/devices/3/rooms","content":"","contentType":"application/json","requestHeaders":"Transaction-Id\u003d@TCID:TIM_V2_BASIS_AF_11X0123/9a5ac82f-fec9-4de2-a74f-3c51b2bf82c6\n\t\t\t\tAccept\u003d*/*\n\t\t\t\tContent-Type\u003dapplication/json","requestCookies":"","responseHeaders":"Date: Sun, 11 Jan 2026 19:21:08 GMT\nContent-Type: application/json\nContent-Length: 523\nConnection: keep-alive\nStrict-Transport-Security: max-age\u003d31536000; includeSubDomains","responseCookies":"","responseBody":"[\n    {\n        \"name\": \"room-!QSeEXFhAqJRWGPkVab:1e6a534d-c4b7-46c4-83d1-4f56e63b6367.ru.timref.akquinet.nx2.dev\",\n        \"roomAccess\": \"private\",\n        \"isEncrypted\": true,\n        \"roomId\": \"!QSeEXFhAqJRWGPkVab:1e6a534d-c4b7-46c4-83d1-4f56e63b6367.ru.timref.akquinet.nx2.dev\",\n        \"members\": [\n            {\n                \"mxid\": \"@tst_generated_qgskfbbjgh:1e6a534d-c4b7-46c4-83d1-4f56e63b6367.ru.timref.akquinet.nx2.dev\",\n                \"membershipState\": \"join\"\n            },\n            {\n                \"mxid\": \"@tst_generated_aafdnvkgdg:0ed5d2be-d54d-4b01-b98a-10f3465ca7b5.ru.timref.akquinet.nx2.dev\",\n                \"membershipState\": \"invite\"\n            }\n        ],\n        \"roomVersion\": \"10\"\n    }\n]","statusCode":200},"precondition":false,"level":3}]},{"number":44,"description":"B join room task","duration":2829,"startTime":"2026-01-11T20:21:08.630023911+01:00[Europe/Berlin]","result":"SUCCESS","reportData":[{"title":"cURL   0","contents":"curl -v -H \"Transaction-Id: @TCID:TIM_V2_BASIS_AF_11X0123/9a5ac82f-fec9-4de2-a74f-3c51b2bf82c6\" -H \"Accept: */*\" -H \"Content-Type: application/json\" -X GET \"http://RU1-Ref-Pract-SDK-HS1/devices/1/rooms\" ","isEvidence":false,"id":"report-data-91facaa1-ee1f-4475-a76e-f51fd467faca"},{"title":"cURL   1","contents":"curl -v -H \"Transaction-Id: @TCID:TIM_V2_BASIS_AF_11X0123/9a5ac82f-fec9-4de2-a74f-3c51b2bf82c6\" -H \"Accept: */*\" -H \"Content-Type: application/json\" -X GET \"http://RU1-Ref-Pract-SDK-HS2/devices/3/rooms\" ","isEvidence":false,"id":"report-data-e7d4aa85-0d1a-4d08-9685-b896380d7516"},{"title":"cURL   2","contents":"curl -v -H \"Transaction-Id: @TCID:TIM_V2_BASIS_AF_11X0123/9a5ac82f-fec9-4de2-a74f-3c51b2bf82c6\" -H \"Accept: */*\" -H \"Content-Type: application/json\" -X POST \"http://RU1-Ref-Pract-SDK-HS2/devices/3/rooms/%21QSeEXFhAqJRWGPkVab%3A1e6a534d-c4b7-46c4-83d1-4f56e63b6367.ru.timref.akquinet.nx2.dev/join\" ","isEvidence":false,"id":"report-data-19cb714c-2fbb-40db-8ca7-f038fda3da3a"}],"precondition":false,"level":2,"children":[{"number":45,"description":"B executes a POST on the resource /devices/{deviceId}/rooms/{roomId}/join","duration":2824,"startTime":"2026-01-11T20:21:08.631824321+01:00[Europe/Berlin]","result":"SUCCESS","precondition":false,"level":3,"children":[{"number":46,"description":"POST http://RU1-Ref-Pract-SDK-HS2/devices/3/rooms/%21QSeEXFhAqJRWGPkVab%3A1e6a534d-c4b7-46c4-83d1-4f56e63b6367.ru.timref.akquinet.nx2.dev/join","duration":0,"startTime":"2026-01-11T20:21:11.456679455+01:00[Europe/Berlin]","result":"SUCCESS","restQuery":{"method":"POST","path":"http://RU1-Ref-Pract-SDK-HS2/devices/3/rooms/%21QSeEXFhAqJRWGPkVab%3A1e6a534d-c4b7-46c4-83d1-4f56e63b6367.ru.timref.akquinet.nx2.dev/join","content":"","contentType":"application/json","requestHeaders":"Transaction-Id\u003d@TCID:TIM_V2_BASIS_AF_11X0123/9a5ac82f-fec9-4de2-a74f-3c51b2bf82c6\n\t\t\t\tAccept\u003d*/*\n\t\t\t\tContent-Type\u003dapplication/json","requestCookies":"","responseHeaders":"Date: Sun, 11 Jan 2026 19:21:11 GMT\nContent-Type: application/json\nContent-Length: 519\nConnection: keep-alive\nStrict-Transport-Security: max-age\u003d31536000; includeSubDomains","responseCookies":"","responseBody":"{\n    \"name\": \"room-!QSeEXFhAqJRWGPkVab:1e6a534d-c4b7-46c4-83d1-4f56e63b6367.ru.timref.akquinet.nx2.dev\",\n    \"roomAccess\": \"private\",\n    \"isEncrypted\": true,\n    \"roomId\": \"!QSeEXFhAqJRWGPkVab:1e6a534d-c4b7-46c4-83d1-4f56e63b6367.ru.timref.akquinet.nx2.dev\",\n    \"members\": [\n        {\n            \"mxid\": \"@tst_generated_qgskfbbjgh:1e6a534d-c4b7-46c4-83d1-4f56e63b6367.ru.timref.akquinet.nx2.dev\",\n            \"membershipState\": \"join\"\n        },\n        {\n            \"mxid\": \"@tst_generated_aafdnvkgdg:0ed5d2be-d54d-4b01-b98a-10f3465ca7b5.ru.timref.akquinet.nx2.dev\",\n            \"membershipState\": \"join\"\n        }\n    ],\n    \"roomVersion\": \"10\"\n}","statusCode":200},"precondition":false,"level":4}]}]}]},{"number":47,"description":"Dann \"B\" empfängt das Attachment \"video.mov\" von \"A\" über Matrix-Protokoll v1.11 als \"m.video\"","duration":817,"startTime":"2026-01-11T20:21:11.664900092+01:00[Europe/Berlin]","result":"SUCCESS","precondition":false,"level":1,"children":[{"number":48,"description":"B executes a GET on the resource /devices/{deviceId}/rooms","duration":80,"startTime":"2026-01-11T20:21:11.667446701+01:00[Europe/Berlin]","result":"SUCCESS","precondition":false,"level":2,"children":[{"number":49,"description":"GET http://RU1-Ref-Pract-SDK-HS2/devices/3/rooms","duration":0,"startTime":"2026-01-11T20:21:11.747471440+01:00[Europe/Berlin]","result":"SUCCESS","restQuery":{"method":"GET","path":"http://RU1-Ref-Pract-SDK-HS2/devices/3/rooms","content":"","contentType":"application/json","requestHeaders":"Transaction-Id\u003d@TCID:TIM_V2_BASIS_AF_11X0123/9a5ac82f-fec9-4de2-a74f-3c51b2bf82c6\n\t\t\t\tAccept\u003d*/*\n\t\t\t\tContent-Type\u003dapplication/json","requestCookies":"","responseHeaders":"Date: Sun, 11 Jan 2026 19:21:11 GMT\nContent-Type: application/json\nContent-Length: 521\nConnection: keep-alive\nStrict-Transport-Security: max-age\u003d31536000; includeSubDomains","responseCookies":"","responseBody":"[\n    {\n        \"name\": \"room-!QSeEXFhAqJRWGPkVab:1e6a534d-c4b7-46c4-83d1-4f56e63b6367.ru.timref.akquinet.nx2.dev\",\n        \"roomAccess\": \"private\",\n        \"isEncrypted\": true,\n        \"roomId\": \"!QSeEXFhAqJRWGPkVab:1e6a534d-c4b7-46c4-83d1-4f56e63b6367.ru.timref.akquinet.nx2.dev\",\n        \"members\": [\n            {\n                \"mxid\": \"@tst_generated_qgskfbbjgh:1e6a534d-c4b7-46c4-83d1-4f56e63b6367.ru.timref.akquinet.nx2.dev\",\n                \"membershipState\": \"join\"\n            },\n            {\n                \"mxid\": \"@tst_generated_aafdnvkgdg:0ed5d2be-d54d-4b01-b98a-10f3465ca7b5.ru.timref.akquinet.nx2.dev\",\n                \"membershipState\": \"join\"\n            }\n        ],\n        \"roomVersion\": \"10\"\n    }\n]","statusCode":200},"precondition":false,"level":3}]},{"number":50,"description":"B executes a GET on the resource /devices/{deviceId}/rooms/{roomId}/messages","duration":290,"startTime":"2026-01-11T20:21:11.751586250+01:00[Europe/Berlin]","result":"SUCCESS","precondition":false,"level":2,"children":[{"number":51,"description":"GET http://RU1-Ref-Pract-SDK-HS2/devices/3/rooms/%21QSeEXFhAqJRWGPkVab%3A1e6a534d-c4b7-46c4-83d1-4f56e63b6367.ru.timref.akquinet.nx2.dev/messages","duration":0,"startTime":"2026-01-11T20:21:12.042460995+01:00[Europe/Berlin]","result":"SUCCESS","restQuery":{"method":"GET","path":"http://RU1-Ref-Pract-SDK-HS2/devices/3/rooms/%21QSeEXFhAqJRWGPkVab%3A1e6a534d-c4b7-46c4-83d1-4f56e63b6367.ru.timref.akquinet.nx2.dev/messages","content":"","contentType":"application/json","requestHeaders":"Transaction-Id\u003d@TCID:TIM_V2_BASIS_AF_11X0123/9a5ac82f-fec9-4de2-a74f-3c51b2bf82c6\n\t\t\t\tAccept\u003d*/*\n\t\t\t\tContent-Type\u003dapplication/json","requestCookies":"","responseHeaders":"Date: Sun, 11 Jan 2026 19:21:12 GMT\nContent-Type: application/json\nContent-Length: 810\nConnection: keep-alive\nStrict-Transport-Security: max-age\u003d31536000; includeSubDomains","responseCookies":"","responseBody":"[\n    {\n        \"body\": \"video.mov\",\n        \"msgtype\": \"m.video\",\n        \"fileId\": \"f71b26fa-bd8e-48e1-8dfb-ec80dfa1b61f\",\n        \"info\": {\n            \"mimetype\": \"video/quicktime\",\n            \"size\": 394733\n        },\n        \"file\": {\n            \"url\": \"mxc://1e6a534d-c4b7-46c4-83d1-4f56e63b6367.ru.timref.akquinet.nx2.dev/FlBFDTTviUyaXMcPonseqHGs\",\n            \"key\": {\n                \"k\": \"AR-M-1ATwcOC-0eIDTM1LNuJwPo4_GQNwHuO_-bUsCo\",\n                \"kty\": \"oct\",\n                \"key_ops\": [\n                    \"encrypt\",\n                    \"decrypt\"\n                ],\n                \"alg\": \"A256CTR\",\n                \"ext\": true\n            },\n            \"iv\": \"Wug8puakqJQAAAAAAAAAAA\",\n            \"hashes\": {\n                \"sha256\": \"gpNiz9mK8+FUEFjY1R6/UioVpxBAW9rNU2XTceJ8vRA\"\n            },\n            \"v\": \"v2\"\n        },\n        \"event_id\": \"$gsEYDo_5rAnnUXJOiENj1pWGikQKBiACllHOO-UMsk8\",\n        \"type\": \"m.room.message\",\n        \"messageId\": \"$gsEYDo_5rAnnUXJOiENj1pWGikQKBiACllHOO-UMsk8\",\n        \"timestamp\": \"2026-01-11T19:21:02.678Z\",\n        \"lastUpdated\": \"2026-01-11T19:21:02.678Z\",\n        \"author\": \"@tst_generated_qgskfbbjgh:1e6a534d-c4b7-46c4-83d1-4f56e63b6367.ru.timref.akquinet.nx2.dev\"\n    }\n]","statusCode":200},"precondition":false,"level":3}]},{"number":52,"description":"B executes a GET on the resource /devices/{deviceId}/media/authenticated/{mediaId}","duration":145,"startTime":"2026-01-11T20:21:12.046169205+01:00[Europe/Berlin]","result":"SUCCESS","precondition":false,"level":2,"children":[{"number":53,"description":"GET http://RU1-Ref-Pract-SDK-HS2/devices/3/media/authenticated/f71b26fa-bd8e-48e1-8dfb-ec80dfa1b61f","duration":0,"startTime":"2026-01-11T20:21:12.191541823+01:00[Europe/Berlin]","result":"SUCCESS","restQuery":{"method":"GET","path":"http://RU1-Ref-Pract-SDK-HS2/devices/3/media/authenticated/f71b26fa-bd8e-48e1-8dfb-ec80dfa1b61f","content":"","contentType":"application/json","requestHeaders":"Transaction-Id\u003d@TCID:TIM_V2_BASIS_AF_11X0123/9a5ac82f-fec9-4de2-a74f-3c51b2bf82c6\n\t\t\t\tAccept\u003d*/*\n\t\t\t\tContent-Type\u003dapplication/json","requestCookies":"","responseHeaders":"Date: Sun, 11 Jan 2026 19:21:12 GMT\nContent-Length: 394733\nConnection: keep-alive\nStrict-Transport-Security: max-age\u003d31536000; includeSubDomains","responseCookies":"","statusCode":200},"precondition":false,"level":3}]},{"number":54,"description":"B executes a GET on the resource /devices/{deviceId}/rooms","duration":81,"startTime":"2026-01-11T20:21:12.195572293+01:00[Europe/Berlin]","result":"SUCCESS","reportData":[{"title":"cURL   0","contents":"curl -v -H \"Transaction-Id: @TCID:TIM_V2_BASIS_AF_11X0123/9a5ac82f-fec9-4de2-a74f-3c51b2bf82c6\" -H \"Accept: */*\" -H \"Content-Type: application/json\" -X GET \"http://RU1-Ref-Pract-SDK-HS2/devices/3/rooms\" ","isEvidence":false,"id":"report-data-01ef2fca-ac85-4c7f-9d9c-1c36edcce10f"},{"title":"cURL   1","contents":"curl -v -H \"Transaction-Id: @TCID:TIM_V2_BASIS_AF_11X0123/9a5ac82f-fec9-4de2-a74f-3c51b2bf82c6\" -H \"Accept: */*\" -H \"Content-Type: application/json\" -X GET \"http://RU1-Ref-Pract-SDK-HS2/devices/3/rooms/%21QSeEXFhAqJRWGPkVab%3A1e6a534d-c4b7-46c4-83d1-4f56e63b6367.ru.timref.akquinet.nx2.dev/messages\" ","isEvidence":false,"id":"report-data-57685bb6-a950-4b3d-8e4d-5c96a0ba2746"},{"title":"cURL   2","contents":"curl -v -H \"Transaction-Id: @TCID:TIM_V2_BASIS_AF_11X0123/9a5ac82f-fec9-4de2-a74f-3c51b2bf82c6\" -H \"Accept: */*\" -H \"Content-Type: application/json\" -X GET \"http://RU1-Ref-Pract-SDK-HS2/devices/3/media/authenticated/f71b26fa-bd8e-48e1-8dfb-ec80dfa1b61f\" ","isEvidence":false,"id":"report-data-f81ed3ea-de1d-4347-8d5c-4ebe0de272de"},{"title":"cURL   3","contents":"curl -v -H \"Transaction-Id: @TCID:TIM_V2_BASIS_AF_11X0123/9a5ac82f-fec9-4de2-a74f-3c51b2bf82c6\" -H \"Accept: */*\" -H \"Content-Type: application/json\" -X GET \"http://RU1-Ref-Pract-SDK-HS2/devices/3/rooms\" ","isEvidence":false,"id":"report-data-3895701c-7d6b-40e7-87bd-e02e87f19059"}],"precondition":false,"level":2,"children":[{"number":55,"description":"GET http://RU1-Ref-Pract-SDK-HS2/devices/3/rooms","duration":0,"startTime":"2026-01-11T20:21:12.276954382+01:00[Europe/Berlin]","result":"SUCCESS","restQuery":{"method":"GET","path":"http://RU1-Ref-Pract-SDK-HS2/devices/3/rooms","content":"","contentType":"application/json","requestHeaders":"Transaction-Id\u003d@TCID:TIM_V2_BASIS_AF_11X0123/9a5ac82f-fec9-4de2-a74f-3c51b2bf82c6\n\t\t\t\tAccept\u003d*/*\n\t\t\t\tContent-Type\u003dapplication/json","requestCookies":"","responseHeaders":"Date: Sun, 11 Jan 2026 19:21:12 GMT\nContent-Type: application/json\nContent-Length: 521\nConnection: keep-alive\nStrict-Transport-Security: max-age\u003d31536000; includeSubDomains","responseCookies":"","responseBody":"[\n    {\n        \"name\": \"room-!QSeEXFhAqJRWGPkVab:1e6a534d-c4b7-46c4-83d1-4f56e63b6367.ru.timref.akquinet.nx2.dev\",\n        \"roomAccess\": \"private\",\n        \"isEncrypted\": true,\n        \"roomId\": \"!QSeEXFhAqJRWGPkVab:1e6a534d-c4b7-46c4-83d1-4f56e63b6367.ru.timref.akquinet.nx2.dev\",\n        \"members\": [\n            {\n                \"mxid\": \"@tst_generated_qgskfbbjgh:1e6a534d-c4b7-46c4-83d1-4f56e63b6367.ru.timref.akquinet.nx2.dev\",\n                \"membershipState\": \"join\"\n            },\n            {\n                \"mxid\": \"@tst_generated_aafdnvkgdg:0ed5d2be-d54d-4b01-b98a-10f3465ca7b5.ru.timref.akquinet.nx2.dev\",\n                \"membershipState\": \"join\"\n            }\n        ],\n        \"roomVersion\": \"10\"\n    }\n]","statusCode":200},"precondition":false,"level":3}]}]},{"number":56,"description":"A executes a GET on the resource /devices/{deviceId}/rooms","duration":77,"startTime":"2026-01-11T20:21:12.483878588+01:00[Europe/Berlin]","result":"SUCCESS","precondition":false,"level":1,"children":[{"number":57,"description":"GET http://RU1-Ref-Pract-SDK-HS1/devices/1/rooms","duration":0,"startTime":"2026-01-11T20:21:12.561081846+01:00[Europe/Berlin]","result":"SUCCESS","restQuery":{"method":"GET","path":"http://RU1-Ref-Pract-SDK-HS1/devices/1/rooms","content":"","contentType":"application/json","requestHeaders":"Transaction-Id\u003d@TCID:TIM_V2_BASIS_AF_11X0123/9a5ac82f-fec9-4de2-a74f-3c51b2bf82c6\n\t\t\t\tAccept\u003d*/*\n\t\t\t\tContent-Type\u003dapplication/json","requestCookies":"","responseHeaders":"Date: Sun, 11 Jan 2026 19:21:12 GMT\nContent-Type: application/json\nContent-Length: 521\nConnection: keep-alive\nStrict-Transport-Security: max-age\u003d31536000; includeSubDomains","responseCookies":"","responseBody":"[\n    {\n        \"name\": \"room-!QSeEXFhAqJRWGPkVab:1e6a534d-c4b7-46c4-83d1-4f56e63b6367.ru.timref.akquinet.nx2.dev\",\n        \"roomAccess\": \"private\",\n        \"isEncrypted\": true,\n        \"roomId\": \"!QSeEXFhAqJRWGPkVab:1e6a534d-c4b7-46c4-83d1-4f56e63b6367.ru.timref.akquinet.nx2.dev\",\n        \"members\": [\n            {\n                \"mxid\": \"@tst_generated_qgskfbbjgh:1e6a534d-c4b7-46c4-83d1-4f56e63b6367.ru.timref.akquinet.nx2.dev\",\n                \"membershipState\": \"join\"\n            },\n            {\n                \"mxid\": \"@tst_generated_aafdnvkgdg:0ed5d2be-d54d-4b01-b98a-10f3465ca7b5.ru.timref.akquinet.nx2.dev\",\n                \"membershipState\": \"join\"\n            }\n        ],\n        \"roomVersion\": \"10\"\n    }\n]","statusCode":200},"precondition":false,"level":2}]},{"number":58,"description":"A leave room task","duration":547,"startTime":"2026-01-11T20:21:12.564017777+01:00[Europe/Berlin]","result":"SUCCESS","precondition":false,"level":1,"children":[{"number":59,"description":"A executes a POST on the resource /devices/{deviceId}/rooms/{roomId}/leave","duration":545,"startTime":"2026-01-11T20:21:12.565375726+01:00[Europe/Berlin]","result":"SUCCESS","precondition":false,"level":2,"children":[{"number":60,"description":"POST http://RU1-Ref-Pract-SDK-HS1/devices/1/rooms/%21QSeEXFhAqJRWGPkVab%3A1e6a534d-c4b7-46c4-83d1-4f56e63b6367.ru.timref.akquinet.nx2.dev/leave","duration":0,"startTime":"2026-01-11T20:21:13.110597798+01:00[Europe/Berlin]","result":"SUCCESS","restQuery":{"method":"POST","path":"http://RU1-Ref-Pract-SDK-HS1/devices/1/rooms/%21QSeEXFhAqJRWGPkVab%3A1e6a534d-c4b7-46c4-83d1-4f56e63b6367.ru.timref.akquinet.nx2.dev/leave","content":"","contentType":"application/json","requestHeaders":"Transaction-Id\u003d@TCID:TIM_V2_BASIS_AF_11X0123/9a5ac82f-fec9-4de2-a74f-3c51b2bf82c6\n\t\t\t\tAccept\u003d*/*\n\t\t\t\tContent-Type\u003dapplication/json","requestCookies":"","responseHeaders":"Date: Sun, 11 Jan 2026 19:21:13 GMT\nContent-Length: 0\nConnection: keep-alive\nStrict-Transport-Security: max-age\u003d31536000; includeSubDomains","responseCookies":"","statusCode":200},"precondition":false,"level":3}]}]},{"number":61,"description":"A forget room task","duration":353,"startTime":"2026-01-11T20:21:13.112295618+01:00[Europe/Berlin]","result":"SUCCESS","precondition":false,"level":1,"children":[{"number":62,"description":"A executes a DELETE on the resource /devices/{deviceId}/rooms/{roomId}","duration":351,"startTime":"2026-01-11T20:21:13.113648358+01:00[Europe/Berlin]","result":"SUCCESS","precondition":false,"level":2,"children":[{"number":63,"description":"DELETE http://RU1-Ref-Pract-SDK-HS1/devices/1/rooms/%21QSeEXFhAqJRWGPkVab%3A1e6a534d-c4b7-46c4-83d1-4f56e63b6367.ru.timref.akquinet.nx2.dev","duration":0,"startTime":"2026-01-11T20:21:13.465562762+01:00[Europe/Berlin]","result":"SUCCESS","restQuery":{"method":"DELETE","path":"http://RU1-Ref-Pract-SDK-HS1/devices/1/rooms/%21QSeEXFhAqJRWGPkVab%3A1e6a534d-c4b7-46c4-83d1-4f56e63b6367.ru.timref.akquinet.nx2.dev","content":"","contentType":"application/json","requestHeaders":"Transaction-Id\u003d@TCID:TIM_V2_BASIS_AF_11X0123/9a5ac82f-fec9-4de2-a74f-3c51b2bf82c6\n\t\t\t\tAccept\u003d*/*\n\t\t\t\tContent-Type\u003dapplication/json","requestCookies":"","responseHeaders":"Date: Sun, 11 Jan 2026 19:21:13 GMT\nConnection: keep-alive\nStrict-Transport-Security: max-age\u003d31536000; includeSubDomains","responseCookies":"","statusCode":204},"precondition":false,"level":3}]}]},{"number":64,"description":"A logout task","duration":134,"startTime":"2026-01-11T20:21:13.467684392+01:00[Europe/Berlin]","result":"SUCCESS","precondition":false,"level":1,"children":[{"number":65,"description":"A executes a POST on the resource /devices/{deviceId}/logout","duration":132,"startTime":"2026-01-11T20:21:13.468689642+01:00[Europe/Berlin]","result":"SUCCESS","precondition":false,"level":2,"children":[{"number":66,"description":"POST http://RU1-Ref-Pract-SDK-HS1/devices/1/logout","duration":0,"startTime":"2026-01-11T20:21:13.601479150+01:00[Europe/Berlin]","result":"SUCCESS","restQuery":{"method":"POST","path":"http://RU1-Ref-Pract-SDK-HS1/devices/1/logout","content":"","contentType":"application/json","requestHeaders":"Transaction-Id\u003d@TCID:TIM_V2_BASIS_AF_11X0123/9a5ac82f-fec9-4de2-a74f-3c51b2bf82c6\n\t\t\t\tAccept\u003d*/*\n\t\t\t\tContent-Type\u003dapplication/json","requestCookies":"","responseHeaders":"Date: Sun, 11 Jan 2026 19:21:13 GMT\nContent-Length: 0\nConnection: keep-alive\nStrict-Transport-Security: max-age\u003d31536000; includeSubDomains","responseCookies":"","statusCode":200},"precondition":false,"level":3}]}]},{"number":67,"description":"A executes a POST on the resource /devices/{deviceId}/unclaim","duration":1332,"startTime":"2026-01-11T20:21:13.603360170+01:00[Europe/Berlin]","result":"SUCCESS","precondition":false,"level":1,"children":[{"number":68,"description":"POST http://RU1-Ref-Pract-SDK-HS1/devices/1/unclaim","duration":0,"startTime":"2026-01-11T20:21:14.935957708+01:00[Europe/Berlin]","result":"SUCCESS","restQuery":{"method":"POST","path":"http://RU1-Ref-Pract-SDK-HS1/devices/1/unclaim","content":"","contentType":"application/json","requestHeaders":"Transaction-Id\u003d@TCID:TIM_V2_BASIS_AF_11X0123/9a5ac82f-fec9-4de2-a74f-3c51b2bf82c6\n\t\t\t\tAccept\u003d*/*\n\t\t\t\tContent-Type\u003dapplication/json","requestCookies":"","responseHeaders":"Date: Sun, 11 Jan 2026 19:21:14 GMT\nContent-Type: application/json\nContent-Length: 95\nConnection: keep-alive\nStrict-Transport-Security: max-age\u003d31536000; includeSubDomains","responseCookies":"","responseBody":"{\n    \"deviceId\": 1,\n    \"deviceName\": \"device-1\",\n    \"deviceStatus\": \"free\",\n    \"claimerName\": \"\",\n    \"claimedUntil\": \"\"\n}","statusCode":200},"precondition":false,"level":2}]},{"number":69,"description":"B executes a GET on the resource /devices/{deviceId}/rooms","duration":76,"startTime":"2026-01-11T20:21:14.937469078+01:00[Europe/Berlin]","result":"SUCCESS","precondition":false,"level":1,"children":[{"number":70,"description":"GET http://RU1-Ref-Pract-SDK-HS2/devices/3/rooms","duration":0,"startTime":"2026-01-11T20:21:15.013587626+01:00[Europe/Berlin]","result":"SUCCESS","restQuery":{"method":"GET","path":"http://RU1-Ref-Pract-SDK-HS2/devices/3/rooms","content":"","contentType":"application/json","requestHeaders":"Transaction-Id\u003d@TCID:TIM_V2_BASIS_AF_11X0123/9a5ac82f-fec9-4de2-a74f-3c51b2bf82c6\n\t\t\t\tAccept\u003d*/*\n\t\t\t\tContent-Type\u003dapplication/json","requestCookies":"","responseHeaders":"Date: Sun, 11 Jan 2026 19:21:15 GMT\nContent-Type: application/json\nContent-Length: 395\nConnection: keep-alive\nStrict-Transport-Security: max-age\u003d31536000; includeSubDomains","responseCookies":"","responseBody":"[\n    {\n        \"name\": \"room-!QSeEXFhAqJRWGPkVab:1e6a534d-c4b7-46c4-83d1-4f56e63b6367.ru.timref.akquinet.nx2.dev\",\n        \"roomAccess\": \"private\",\n        \"isEncrypted\": true,\n        \"roomId\": \"!QSeEXFhAqJRWGPkVab:1e6a534d-c4b7-46c4-83d1-4f56e63b6367.ru.timref.akquinet.nx2.dev\",\n        \"members\": [\n            {\n                \"mxid\": \"@tst_generated_aafdnvkgdg:0ed5d2be-d54d-4b01-b98a-10f3465ca7b5.ru.timref.akquinet.nx2.dev\",\n                \"membershipState\": \"join\"\n            }\n        ],\n        \"roomVersion\": \"10\"\n    }\n]","statusCode":200},"precondition":false,"level":2}]},{"number":71,"description":"B leave room task","duration":589,"startTime":"2026-01-11T20:21:15.016299056+01:00[Europe/Berlin]","result":"SUCCESS","precondition":false,"level":1,"children":[{"number":72,"description":"B executes a POST on the resource /devices/{deviceId}/rooms/{roomId}/leave","duration":587,"startTime":"2026-01-11T20:21:15.017732416+01:00[Europe/Berlin]","result":"SUCCESS","precondition":false,"level":2,"children":[{"number":73,"description":"POST http://RU1-Ref-Pract-SDK-HS2/devices/3/rooms/%21QSeEXFhAqJRWGPkVab%3A1e6a534d-c4b7-46c4-83d1-4f56e63b6367.ru.timref.akquinet.nx2.dev/leave","duration":0,"startTime":"2026-01-11T20:21:15.605405647+01:00[Europe/Berlin]","result":"SUCCESS","restQuery":{"method":"POST","path":"http://RU1-Ref-Pract-SDK-HS2/devices/3/rooms/%21QSeEXFhAqJRWGPkVab%3A1e6a534d-c4b7-46c4-83d1-4f56e63b6367.ru.timref.akquinet.nx2.dev/leave","content":"","contentType":"application/json","requestHeaders":"Transaction-Id\u003d@TCID:TIM_V2_BASIS_AF_11X0123/9a5ac82f-fec9-4de2-a74f-3c51b2bf82c6\n\t\t\t\tAccept\u003d*/*\n\t\t\t\tContent-Type\u003dapplication/json","requestCookies":"","responseHeaders":"Date: Sun, 11 Jan 2026 19:21:15 GMT\nContent-Length: 0\nConnection: keep-alive\nStrict-Transport-Security: max-age\u003d31536000; includeSubDomains","responseCookies":"","statusCode":200},"precondition":false,"level":3}]}]},{"number":74,"description":"B forget room task","duration":396,"startTime":"2026-01-11T20:21:15.607210136+01:00[Europe/Berlin]","result":"SUCCESS","precondition":false,"level":1,"children":[{"number":75,"description":"B executes a DELETE on the resource /devices/{deviceId}/rooms/{roomId}","duration":394,"startTime":"2026-01-11T20:21:15.608593536+01:00[Europe/Berlin]","result":"SUCCESS","precondition":false,"level":2,"children":[{"number":76,"description":"DELETE http://RU1-Ref-Pract-SDK-HS2/devices/3/rooms/%21QSeEXFhAqJRWGPkVab%3A1e6a534d-c4b7-46c4-83d1-4f56e63b6367.ru.timref.akquinet.nx2.dev","duration":0,"startTime":"2026-01-11T20:21:16.002988600+01:00[Europe/Berlin]","result":"SUCCESS","restQuery":{"method":"DELETE","path":"http://RU1-Ref-Pract-SDK-HS2/devices/3/rooms/%21QSeEXFhAqJRWGPkVab%3A1e6a534d-c4b7-46c4-83d1-4f56e63b6367.ru.timref.akquinet.nx2.dev","content":"","contentType":"application/json","requestHeaders":"Transaction-Id\u003d@TCID:TIM_V2_BASIS_AF_11X0123/9a5ac82f-fec9-4de2-a74f-3c51b2bf82c6\n\t\t\t\tAccept\u003d*/*\n\t\t\t\tContent-Type\u003dapplication/json","requestCookies":"","responseHeaders":"Date: Sun, 11 Jan 2026 19:21:15 GMT\nConnection: keep-alive\nStrict-Transport-Security: max-age\u003d31536000; includeSubDomains","responseCookies":"","statusCode":204},"precondition":false,"level":3}]}]},{"number":77,"description":"B logout task","duration":153,"startTime":"2026-01-11T20:21:16.004772970+01:00[Europe/Berlin]","result":"SUCCESS","precondition":false,"level":1,"children":[{"number":78,"description":"B executes a POST on the resource /devices/{deviceId}/logout","duration":152,"startTime":"2026-01-11T20:21:16.005766690+01:00[Europe/Berlin]","result":"SUCCESS","precondition":false,"level":2,"children":[{"number":79,"description":"POST http://RU1-Ref-Pract-SDK-HS2/devices/3/logout","duration":0,"startTime":"2026-01-11T20:21:16.158212538+01:00[Europe/Berlin]","result":"SUCCESS","restQuery":{"method":"POST","path":"http://RU1-Ref-Pract-SDK-HS2/devices/3/logout","content":"","contentType":"application/json","requestHeaders":"Transaction-Id\u003d@TCID:TIM_V2_BASIS_AF_11X0123/9a5ac82f-fec9-4de2-a74f-3c51b2bf82c6\n\t\t\t\tAccept\u003d*/*\n\t\t\t\tContent-Type\u003dapplication/json","requestCookies":"","responseHeaders":"Date: Sun, 11 Jan 2026 19:21:16 GMT\nContent-Length: 0\nConnection: keep-alive\nStrict-Transport-Security: max-age\u003d31536000; includeSubDomains","responseCookies":"","statusCode":200},"precondition":false,"level":3}]}]},{"number":80,"description":"B executes a POST on the resource /devices/{deviceId}/unclaim","duration":247,"startTime":"2026-01-11T20:21:16.160307508+01:00[Europe/Berlin]","result":"SUCCESS","reportData":[{"title":"Rohdaten-Statistik-Total","contents":"TIM.UC_10057_01 (Client-Login, Auswahl Authentifizierungsverfahren):\n\t   Erfolgreich:\t  128\n\tFehlgeschlagen:\t    0\n\n TIM.UC_10057_02 (Erstellung Matrix-ACCESS_TOKEN):\n\t   Erfolgreich:\t  128\n\tFehlgeschlagen:\t    0\n\n TIM.UC_10057_03 (Erstellung Matrix-OpenID-Token):\n\t   Erfolgreich:\t  128\n\tFehlgeschlagen:\t    0\n\n TIM.UC_10104-01_01 (Akteur suchen):\n\t   Erfolgreich:\t   12\n\tFehlgeschlagen:\t    0\n\n TIM.UC_10104-01_02 (Akteur einladen, gleicher Homeserver):\n\t   Erfolgreich:\t   17\n\tFehlgeschlagen:\t    0\n\n TIM.UC_10063_01 (Austausch von Events innerhalb einer Organisation, gleicher Homeserver):\n\t   Erfolgreich:\t   26\n\tFehlgeschlagen:\t    0\n\n TIM.UC_10061-01_01 (Eintrag in Freigabeliste erzeugen):\n\t   Erfolgreich:\t    0\n\tFehlgeschlagen:\t    0\n\n TIM.UC_10061-01_02 (Einladung Sendersystem, unterschiedliche Homeserver):\n\t   Erfolgreich:\t   30\n\tFehlgeschlagen:\t    1\n\t[HTTP/1.1 403 Forbidden]\n\n TIM.UC_10061-01_03 (Einladung Empfangssystem, unterschiedliche Homeserver):\n\t   Erfolgreich:\t   30\n\tFehlgeschlagen:\t    1\n\t[HTTP/1.1 403 Forbidden]\n\n TIM.UC_10062-01_01 (Event Sendersystem, unterschiedliche Homeserver):\n\t   Erfolgreich:\t   32\n\tFehlgeschlagen:\t    0\n\n TIM.UC_10062-01_02 (Event Empfangssystem, unterschiedliche Homeserver):\n\t   Erfolgreich:\t   32\n\tFehlgeschlagen:\t    0\n\n TIM.UC_10059-01_02 (Organisationsressourcen im Verzeichnisdienst hinzufügen):\n\t   Erfolgreich:\t   13\n\tFehlgeschlagen:\t    0\n\n","isEvidence":false,"id":"report-data-0e63f0b3-759a-45d6-9747-cbcef1909a42"},{"title":"Rohdaten-Statistik","contents":"TIM.UC_10057_01 (Client-Login, Auswahl Authentifizierungsverfahren):\n\t   Erfolgreich:\t    2\n\tFehlgeschlagen:\t    0\n\n TIM.UC_10057_02 (Erstellung Matrix-ACCESS_TOKEN):\n\t   Erfolgreich:\t    2\n\tFehlgeschlagen:\t    0\n\n TIM.UC_10057_03 (Erstellung Matrix-OpenID-Token):\n\t   Erfolgreich:\t    2\n\tFehlgeschlagen:\t    0\n\n TIM.UC_10104-01_01 (Akteur suchen):\n\t   Erfolgreich:\t    0\n\tFehlgeschlagen:\t    0\n\n TIM.UC_10104-01_02 (Akteur einladen, gleicher Homeserver):\n\t   Erfolgreich:\t    0\n\tFehlgeschlagen:\t    0\n\n TIM.UC_10063_01 (Austausch von Events innerhalb einer Organisation, gleicher Homeserver):\n\t   Erfolgreich:\t    0\n\tFehlgeschlagen:\t    0\n\n TIM.UC_10061-01_01 (Eintrag in Freigabeliste erzeugen):\n\t   Erfolgreich:\t    0\n\tFehlgeschlagen:\t    0\n\n TIM.UC_10061-01_02 (Einladung Sendersystem, unterschiedliche Homeserver):\n\t   Erfolgreich:\t    1\n\tFehlgeschlagen:\t    0\n\n TIM.UC_10061-01_03 (Einladung Empfangssystem, unterschiedliche Homeserver):\n\t   Erfolgreich:\t    1\n\tFehlgeschlagen:\t    0\n\n TIM.UC_10062-01_01 (Event Sendersystem, unterschiedliche Homeserver):\n\t   Erfolgreich:\t    1\n\tFehlgeschlagen:\t    0\n\n TIM.UC_10062-01_02 (Event Empfangssystem, unterschiedliche Homeserver):\n\t   Erfolgreich:\t    1\n\tFehlgeschlagen:\t    0\n\n TIM.UC_10059-01_02 (Organisationsressourcen im Verzeichnisdienst hinzufügen):\n\t   Erfolgreich:\t    0\n\tFehlgeschlagen:\t    0\n\n","isEvidence":false,"id":"report-data-130e46ed-c35a-4aaf-8057-b559c1a31b8c"}],"precondition":false,"level":1,"children":[{"number":81,"description":"POST http://RU1-Ref-Pract-SDK-HS2/devices/3/unclaim","duration":0,"startTime":"2026-01-11T20:21:16.407406953+01:00[Europe/Berlin]","result":"SUCCESS","restQuery":{"method":"POST","path":"http://RU1-Ref-Pract-SDK-HS2/devices/3/unclaim","content":"","contentType":"application/json","requestHeaders":"Transaction-Id\u003d@TCID:TIM_V2_BASIS_AF_11X0123/9a5ac82f-fec9-4de2-a74f-3c51b2bf82c6\n\t\t\t\tAccept\u003d*/*\n\t\t\t\tContent-Type\u003dapplication/json","requestCookies":"","responseHeaders":"Date: Sun, 11 Jan 2026 19:21:16 GMT\nContent-Type: application/json\nContent-Length: 95\nConnection: keep-alive\nStrict-Transport-Security: max-age\u003d31536000; includeSubDomains","responseCookies":"","responseBody":"{\n    \"deviceId\": 3,\n    \"deviceName\": \"device-3\",\n    \"deviceStatus\": \"free\",\n    \"claimerName\": \"\",\n    \"claimedUntil\": \"\"\n}","statusCode":200},"precondition":false,"level":2}]}]}],"userStory":{"id":"UCs_Basis/UC11X_MessageTypes/11X_1_OrgOrg_MessageTypes_V2_Basis","storyName":"11X. (1) Message Types (Basis Spec)","displayName":"11X. (1) Message Types (Basis Spec)","path":"UCs_Basis/UC11X_MessageTypes/11X_1_OrgOrg_MessageTypes_V2_Basis","pathElements":[{"name":"UCs_Basis","description":""},{"name":"UC11X_MessageTypes","description":""},{"name":"11X_1_OrgOrg_MessageTypes_V2_Basis","description":""}],"narrative":"  In diesen Testfällen soll das Versenden und Empfangen von den in Matrix spezifizierten Message Types (inkl. ihrer\n  Konformität zur Matrix Spezifiaktion) überprüft werden.\n\n  Wichtig: Die Gematik behält sich vor die Typen/Files der Attachments (m.image, m.file, m.audio, m.video) jederzeit zu\n  ändern oder zu erweitern, da die Struktur dieser Matrix-Events davon unbetroffen ist.\n\n  COMMENT: Basis\n  A_25395-01   Matrix Module - Instant Messaging\n\n  Inhalt\n  TF  1 -  2  m.text (Chat/Raum)\n  TF  3 -  4  m.emote (Chat/Raum)\n  TF  5 -  6  m.notice (Chat/Raum)\n  TF  7 -  8  m.location (Chat/Raum)\n  TF  9 - 12  m.image (Chat/Raum) (jpg,png)\n  TF 13 - 16  m.file (Chat/Raum) (txt,pdf)\n  TF 17 - 20  m.audio (Chat/Raum) (mp3,wav)\n  TF 21 - 24  m.video (Chat/Raum) (mp4,mov)","type":"feature"},"title":"11X.01.23 Message Types - Chat - AllowAll - Org-User sendet ein m.video Attachment (mov) über Matrix-Protokoll v1.11 an Org-User","description":"","tags":[{"name":"Positiv","type":"TESTFALL","displayName":"Positiv","rawStringFromValueTag":"TESTFALL:Positiv"},{"name":"Filter(ApiName1.hasTag(\"proClient\"))","type":"Plugin","displayName":"Filter(ApiName1.hasTag(\"proClient\"))","rawStringFromValueTag":"Plugin:Filter(ApiName1.hasTag(\"proClient\"))"},{"name":"1","type":"PRIO","displayName":"1","rawStringFromValueTag":"PRIO:1"},{"name":"AllowDoubleLineup(true)","type":"Plugin","displayName":"AllowDoubleLineup(true)","rawStringFromValueTag":"Plugin:AllowDoubleLineup(true)"},{"name":"AllowSelfCombine(false)","type":"Plugin","displayName":"AllowSelfCombine(false)","rawStringFromValueTag":"Plugin:AllowSelfCombine(false)"},{"name":"MsgType","type":"Ctl","displayName":"MsgType","rawStringFromValueTag":"Ctl:MsgType"},{"name":"Attachment","type":"Ctl","displayName":"Attachment","rawStringFromValueTag":"Ctl:Attachment"},{"name":"DistinctProperty(homeserver)","type":"Plugin","displayName":"DistinctProperty(homeserver)","rawStringFromValueTag":"Plugin:DistinctProperty(homeserver)"},{"name":"FeatureFile_11X_01_V2_Basis","type":"File","displayName":"FeatureFile_11X_01_V2_Basis","rawStringFromValueTag":"File:FeatureFile_11X_01_V2_Basis"},{"name":"Filter(ApiName2.hasTag(\"proClient\"))","type":"Plugin","displayName":"Filter(ApiName2.hasTag(\"proClient\"))","rawStringFromValueTag":"Plugin:Filter(ApiName2.hasTag(\"proClient\"))"},{"name":"Pro","type":"Zul","displayName":"Pro","rawStringFromValueTag":"Zul:Pro"},{"name":"Shuffle(true)","type":"Plugin","displayName":"Shuffle(true)","rawStringFromValueTag":"Plugin:Shuffle(true)"},{"name":"AllowAll","type":"Ctl","displayName":"AllowAll","rawStringFromValueTag":"Ctl:AllowAll"},{"name":"TI-M_Client_Basis","type":"PRODUKT","displayName":"TI-M_Client_Basis","rawStringFromValueTag":"PRODUKT:TI-M_Client_Basis"},{"name":"A_25395-01","type":"AFO-ID","displayName":"A_25395-01","rawStringFromValueTag":"AFO-ID:A_25395-01"},{"name":"TIM_V2_BASIS_AF_11X0123","type":"TCID","displayName":"TIM_V2_BASIS_AF_11X0123","rawStringFromValueTag":"TCID:TIM_V2_BASIS_AF_11X0123"},{"name":"UseCaseV2_11X_Basis","type":"Ctl","displayName":"UseCaseV2_11X_Basis","rawStringFromValueTag":"Ctl:UseCaseV2_11X_Basis"},{"name":"TI-M_FD_Basis","type":"PRODUKT","displayName":"TI-M_FD_Basis","rawStringFromValueTag":"PRODUKT:TI-M_FD_Basis"},{"name":"Implementiert","type":"STATUS","displayName":"Implementiert","rawStringFromValueTag":"STATUS:Implementiert"},{"name":"JA","type":"NB","displayName":"JA","rawStringFromValueTag":"NB:JA"},{"name":"ProKK","type":"Zul","displayName":"ProKK","rawStringFromValueTag":"Zul:ProKK"}],"startTime":"2026-01-11T20:20:01.516968705+01:00[Europe/Berlin]","endTime":"2026-01-11T20:21:16.409928313+01:00[Europe/Berlin]","duration":1826,"projectKey":"","isManualTestingUpToDate":false,"dataTable":{"headers":["ApiName1","ApiName2"],"rows":[{"values":["RU1-Ref-Pract-SDK-HS1","RU1-Ref-Pract-SDK-HS2"],"lineNumber":443,"result":"SUCCESS"}],"predefinedRows":true,"scenarioOutline":"Angenommen Es werden folgende Clients reserviert:\n\rUnd \"A\", \"B\" setzen den eigenen Authorization Mode auf \"AllowAll\"\n\rWenn \"A\" sendet ein Attachment \"video.mov\" direkt an \"B\" als \"m.video\"\n\rUnd \"B\" erhält eine Einladung von \"A\"\n\rUnd \"B\" bestätigt eine Einladung von \"A\"\n\rDann \"B\" empfängt das Attachment \"video.mov\" von \"A\" über Matrix-Protokoll v1.11 als \"m.video\"\n\r","dataSetDescriptors":[{"startRow":0,"rowCount":0,"name":"","description":"","tags":[{"name":"Shuffle(true)","type":"Plugin","displayName":"Shuffle(true)","rawStringFromValueTag":"Plugin:Shuffle(true)"},{"name":"DistinctProperty(homeserver)","type":"Plugin","displayName":"DistinctProperty(homeserver)","rawStringFromValueTag":"Plugin:DistinctProperty(homeserver)"},{"name":"AllowSelfCombine(false)","type":"Plugin","displayName":"AllowSelfCombine(false)","rawStringFromValueTag":"Plugin:AllowSelfCombine(false)"},{"name":"AllowDoubleLineup(true)","type":"Plugin","displayName":"AllowDoubleLineup(true)","rawStringFromValueTag":"Plugin:AllowDoubleLineup(true)"},{"name":"Filter(ApiName1.hasTag(\"proClient\"))","type":"Plugin","displayName":"Filter(ApiName1.hasTag(\"proClient\"))","rawStringFromValueTag":"Plugin:Filter(ApiName1.hasTag(\"proClient\"))"},{"name":"Filter(ApiName2.hasTag(\"proClient\"))","type":"Plugin","displayName":"Filter(ApiName2.hasTag(\"proClient\"))","rawStringFromValueTag":"Plugin:Filter(ApiName2.hasTag(\"proClient\"))"}]}]},"manual":false,"testSource":"Cucumber","actors":[{"name":"A","can":["call an API at http://RU1-Ref-Pract-SDK-HS1","de.gematik.tim.test.glue.api.devices.UseDeviceAbility@2fa21811","de.gematik.tim.test.glue.api.login.IsLoggedInAbility@3b6fff70","de.gematik.tim.test.glue.api.room.UseRoomAbility@4e8c8f13"]},{"name":"B","can":["call an API at http://RU1-Ref-Pract-SDK-HS2","de.gematik.tim.test.glue.api.devices.UseDeviceAbility@685a8f45","de.gematik.tim.test.glue.api.login.IsLoggedInAbility@5c592bba","de.gematik.tim.test.glue.api.room.UseRoomAbility@e2d3658"]}],"order":0,"result":"SUCCESS","scenarioOutline":"Angenommen Es werden folgende Clients reserviert:\n|A | PRO_CLIENT | \u003cApiName1\u003e|\n|B | PRO_CLIENT | \u003cApiName2\u003e|\nUnd \"A\", \"B\" setzen den eigenen Authorization Mode auf \"AllowAll\"\nWenn \"A\" sendet ein Attachment \"video.mov\" direkt an \"B\" als \"m.video\"\nUnd \"B\" erhält eine Einladung von \"A\"\nUnd \"B\" bestätigt eine Einladung von \"A\"\nDann \"B\" empfängt das Attachment \"video.mov\" von \"A\" über Matrix-Protokoll v1.11 als \"m.video\""}